MANIFEST.in
README.md
README.rst
nesting.py
setup.py
nesting.egg-info/PKG-INFO
nesting.egg-info/SOURCES.txt
nesting.egg-info/dependency_links.txt
nesting.egg-info/not-zip-safe
nesting.egg-info/top_level.txt