Metadata-Version: 1.1
Name: nesting
Version: 0.1.0
Summary: Operator to construct nested rollups from lists of records.
Home-page: https://github.com/dsc/nesting
Author: David Schoonover
Author-email: dsc@less.ly
License: MIT
Keywords: nesting operator data series
Platform: UNKNOWN
Classifier: Development Status :: 4 - Beta
Classifier: Environment :: Console
Classifier: Intended Audience :: Developers
Classifier: Topic :: Utilities
Classifier: Topic :: Software Development :: Libraries :: Python Modules
Classifier: Programming Language :: Python
Classifier: Programming Language :: Python :: 2.6
Classifier: Programming Language :: Python :: 2.7
Classifier: Operating System :: OS Independent
Classifier: License :: OSI Approved :: MIT License
